celery_beat_rest/__init__.py
celery_beat_rest/fields.py
celery_beat_rest/filters.py
celery_beat_rest/serializers.py
celery_beat_rest/urls.py
celery_beat_rest/views.py
django_celery_beat_rest-0.0.5.dist-info/LICENSE
django_celery_beat_rest-0.0.5.dist-info/METADATA
django_celery_beat_rest-0.0.5.dist-info/WHEEL
django_celery_beat_rest-0.0.5.dist-info/top_level.txt
django_celery_beat_rest-0.0.5.dist-info/RECORD
