Metadata-Version: 2.1
Name: django-celery-beat-rest
Version: 0.0.5
Summary: RESTful API for django-celery-beat
Author: zengqiu
Author-email: zengqiu@qq.com
License: MIT
Platform: any
Classifier: Development Status :: 5 - Production/Stable
Classifier: Environment :: Web Environment
Classifier: Intended Audience :: Developers
Classifier: License :: OSI Approved :: MIT License
Classifier: Operating System :: OS Independent
Classifier: Programming Language :: Python
Classifier: Programming Language :: Python :: 3 :: Only
Classifier: Programming Language :: Python :: 3.7
Classifier: Programming Language :: Python :: 3.8
Classifier: Programming Language :: Python :: 3.9
Classifier: Programming Language :: Python :: 3.10
Classifier: Programming Language :: Python :: 3.11
Classifier: Topic :: Internet :: WWW/HTTP :: Dynamic Content
Classifier: Topic :: Software Development :: Libraries :: Python Modules
Requires-Python: >=3.5
License-File: LICENSE
Requires-Dist: django-celery-beat >=2.5.0
Requires-Dist: djangorestframework >=3.14.0
Requires-Dist: django-filter >=23.5
